EBIOXP0919_intf/__init__.py
EBIOXP0919_intf/ebioxp0919.py
EBIOXP0919-0.1.5.dist-info/LICENSE
EBIOXP0919-0.1.5.dist-info/METADATA
EBIOXP0919-0.1.5.dist-info/WHEEL
EBIOXP0919-0.1.5.dist-info/top_level.txt
EBIOXP0919-0.1.5.dist-info/RECORD
