Metadata-Version: 2.1
Name: EBIOXP0919
Version: 0.1.5
Summary: Python interface to interact with EBIOXP0919-4I4O board using Raspberry Pi
Author: ElectronBits
Author-email: info@electronbits.com
Project-URL: Website, https://www.electronbits.com
Project-URL: Source, https://github.com/electronbits/Py_EBIOXP0919
Classifier: Programming Language :: Python :: 3
Classifier: License :: OSI Approved :: MIT License
Classifier: Operating System :: POSIX :: Linux
Requires-Python: >=3.6
License-File: LICENSE
Requires-Dist: smbus
